spanishconjugator/SpanishConjugator.py
spanishconjugator/__init__.py
spanishconjugator/irregulars/__init__.py
spanishconjugator/irregulars/irregular_dict.py
spanishconjugator/tenses/__init__.py
spanishconjugator/tenses/conditional/__init__.py
spanishconjugator/tenses/conditional/perfect.py
spanishconjugator/tenses/conditional/simple_conditional.py
spanishconjugator/tenses/imperative/__init__.py
spanishconjugator/tenses/imperative/affirmative.py
spanishconjugator/tenses/imperative/negative.py
spanishconjugator/tenses/indicative/__init__.py
spanishconjugator/tenses/indicative/future.py
spanishconjugator/tenses/indicative/future_perfect.py
spanishconjugator/tenses/indicative/imperfect.py
spanishconjugator/tenses/indicative/past_anterior.py
spanishconjugator/tenses/indicative/past_perfect.py
spanishconjugator/tenses/indicative/present.py
spanishconjugator/tenses/indicative/present_perfect.py
spanishconjugator/tenses/indicative/preterite.py
spanishconjugator/tenses/subjunctive/__init__.py
spanishconjugator/tenses/subjunctive/future.py
spanishconjugator/tenses/subjunctive/future_perfect.py
spanishconjugator/tenses/subjunctive/imperfect.py
spanishconjugator/tenses/subjunctive/imperfect_se.py
spanishconjugator/tenses/subjunctive/pluperfect.py
spanishconjugator/tenses/subjunctive/present.py
spanishconjugator/tenses/subjunctive/present_perfect.py
spanishconjugator-2.3.9474.dist-info/LICENSE.txt
spanishconjugator-2.3.9474.dist-info/METADATA
spanishconjugator-2.3.9474.dist-info/WHEEL
spanishconjugator-2.3.9474.dist-info/top_level.txt
spanishconjugator-2.3.9474.dist-info/RECORD
