Metadata-Version: 2.1
Name: spanishconjugator
Version: 2.3.9474
Summary: A python library to conjugate spanish words with parameters tense, mood and pronoun
Home-page: https://github.com/Benedict-Carling/spanish-conjugator
Author: Benedict Carling
Author-email: bencarling1@gmail.com
Classifier: Programming Language :: Python :: 3
Classifier: Programming Language :: Python :: 3.6
Classifier: Programming Language :: Python :: 3.7
Classifier: Programming Language :: Python :: 3.8
Classifier: License :: OSI Approved :: MIT License
Classifier: Natural Language :: English
Classifier: Operating System :: OS Independent
License-File: LICENSE.txt
Provides-Extra: dev
Requires-Dist: pytest; extra == "dev"
Requires-Dist: check-manifest; extra == "dev"
Requires-Dist: twine; extra == "dev"
